pybpodgui_plugin_session_history/__init__.py
pybpodgui_plugin_session_history/session_history.py
pybpodgui_plugin_session_history/settings.py
pybpodgui_plugin_session_history/models/__init__.py
pybpodgui_plugin_session_history/models/session/__init__.py
pybpodgui_plugin_session_history/models/session/session_treenode.py
pybpodgui_plugin_session_history/models/subject/__init__.py
pybpodgui_plugin_session_history/models/subject/subject_treenode.py
pybpodgui_plugin_session_history/resources/history.png
pybpod_gui_plugin_session_history-1.4.2.dist-info/LICENSE
pybpod_gui_plugin_session_history-1.4.2.dist-info/METADATA
pybpod_gui_plugin_session_history-1.4.2.dist-info/WHEEL
pybpod_gui_plugin_session_history-1.4.2.dist-info/top_level.txt
pybpod_gui_plugin_session_history-1.4.2.dist-info/RECORD
