Metadata-Version: 2.1
Name: pybpod-gui-plugin-session-history
Version: 1.4.2
Summary: PyBpod GUI session log plugin
Home-page: https://github.com/pybpod/pybpod-gui-plugin-session-history
Author: Carlos Mão de Ferro, Ricardo Jorge Vieira Ribeiro, Luís Teixeira
Author-email: cajomferro@gmail.com, ricardojvr@gmail.com, micboucinha@gmail.com
License: MIT
Platform: UNKNOWN
